onnx_graphsurgeon/__init__.py
onnx_graphsurgeon/exporters/__init__.py
onnx_graphsurgeon/exporters/base_exporter.py
onnx_graphsurgeon/exporters/onnx_exporter.py
onnx_graphsurgeon/importers/__init__.py
onnx_graphsurgeon/importers/base_importer.py
onnx_graphsurgeon/importers/onnx_importer.py
onnx_graphsurgeon/ir/__init__.py
onnx_graphsurgeon/ir/graph.py
onnx_graphsurgeon/ir/node.py
onnx_graphsurgeon/ir/tensor.py
onnx_graphsurgeon/logger/__init__.py
onnx_graphsurgeon/logger/logger.py
onnx_graphsurgeon/util/__init__.py
onnx_graphsurgeon/util/exception.py
onnx_graphsurgeon/util/misc.py
modlee_onnx_graphsurgeon-0.3.27.dist-info/LICENSE
modlee_onnx_graphsurgeon-0.3.27.dist-info/METADATA
modlee_onnx_graphsurgeon-0.3.27.dist-info/WHEEL
modlee_onnx_graphsurgeon-0.3.27.dist-info/top_level.txt
modlee_onnx_graphsurgeon-0.3.27.dist-info/zip-safe
modlee_onnx_graphsurgeon-0.3.27.dist-info/RECORD
