Metadata-Version: 2.1
Name: modlee-onnx_graphsurgeon
Version: 0.3.27
Summary: ONNX GraphSurgeon
Home-page: https://github.com/modlee-ai/TensorRT/tree/release/8.6/tools/onnx-graphsurgeon
Author: NVIDIA
Author-email: svc_tensorrt@nvidia.com
License: Apache 2.0
Classifier: Intended Audience :: Developers
Classifier: Programming Language :: Python :: 3
Classifier: Programming Language :: Python :: 3.4
Classifier: Programming Language :: Python :: 3.5
Classifier: Programming Language :: Python :: 3.6
Classifier: Programming Language :: Python :: 3.7
Classifier: Programming Language :: Python :: 3.8
License-File: LICENSE
Requires-Dist: numpy
Requires-Dist: onnx
